README.md
setup.py
band_etl.egg-info/PKG-INFO
band_etl.egg-info/SOURCES.txt
band_etl.egg-info/dependency_links.txt
band_etl.egg-info/entry_points.txt
band_etl.egg-info/requires.txt
band_etl.egg-info/top_level.txt
bandetl/__init__.py
bandetl/__main__.py
bandetl/cli/__init__.py
bandetl/cli/export_blocks.py
bandetl/cli/get_block_range_for_date.py
bandetl/cli/stream.py
bandetl/enumeration/__init__.py
bandetl/enumeration/entity_type.py
bandetl/jobs/__init__.py
bandetl/jobs/export_blocks_job.py
bandetl/jobs/exporters/__init__.py
bandetl/jobs/exporters/band_item_exporter.py
bandetl/mappers/__init__.py
bandetl/mappers/block_event_mapper.py
bandetl/mappers/block_mapper.py
bandetl/mappers/log_mapper.py
bandetl/mappers/message_mapper.py
bandetl/mappers/oracle_request_mapper.py
bandetl/mappers/transaction_mapper.py
bandetl/rpc/__init__.py
bandetl/rpc/band_rpc.py
bandetl/rpc/request.py
bandetl/rpc/tendermint_rpc.py
bandetl/service/__init__.py
bandetl/service/band_block_range_service.py
bandetl/service/band_block_timestamp_graph.py
bandetl/service/band_service.py
bandetl/streaming/__init__.py
bandetl/streaming/band_streamer_adapter.py
bandetl/streaming/item_exporter_creator.py
bandetl/streaming/item_id_calculator.py
bandetl/utils/__init__.py
bandetl/utils/band_utils.py
bandetl/utils/datetime_utils.py
bandetl/utils/string_utils.py
tests/bandetl/__init__.py
tests/bandetl/helpers.py
tests/bandetl/mock_band_rpc.py
tests/bandetl/mock_tendermint_rpc.py
tests/resources/__init__.py