Metadata-Version: 2.1
Name: band-etl
Version: 0.0.8
Summary: Tools for exporting Band Protocol blockchain data to JSON
Home-page: https://github.com/blockchain-etl/band-etl
Author: Evgeny Medvedev
Author-email: evge.medvedev@gmail.com
License: UNKNOWN
Project-URL: Bug Reports, https://github.com/blockchain-etl/band-etl/issues
Project-URL: Source, https://github.com/blockchain-etl/band-etl
Keywords: Band Protocol
Platform: UNKNOWN
Classifier: Development Status :: 5 - Production/Stable
Classifier: Intended Audience :: Developers
Classifier: License :: OSI Approved :: MIT License
Classifier: Programming Language :: Python :: 3
Classifier: Programming Language :: Python :: 3.6
Classifier: Programming Language :: Python :: 3.7
Requires-Python: >=3.6.0,<3.8.0
Provides-Extra: streaming
Provides-Extra: dev
